pandas_sklearn
