Metadata-Version: 1.0
Name: pandas2sklearn
Version: 0.0.3
Summary: An integration of pandas dataframes with scikit learn.
Home-page: https://github.com/mouradmourafiq/pandas2sklearn
Author: Mourad Mourafiq
Author-email: mouradmourafiq@gmail.com
License: MIT
Keywords: scikit,sklearn,pandas
Platform: any
